interviewlib/__init__.py
interviewlib/core.py
interviewlib/demo.py
interviewlib-0.1.1.dist-info/METADATA
interviewlib-0.1.1.dist-info/WHEEL
interviewlib-0.1.1.dist-info/top_level.txt
interviewlib-0.1.1.dist-info/RECORD
