Metadata-Version: 2.4
Name: interviewlib
Version: 0.1.1
Summary: Python interview questions and solutions library
Home-page: https://github.com/MUSTAKIMSHAIKH2942/interviewlib
Author: Mustakim Shaikh
Author-email: mustakim.shaikh.prof@gmail.com
License: MIT
Classifier: Programming Language :: Python :: 3
Classifier: License :: OSI Approved :: MIT License
Classifier: Operating System :: OS Independent
Requires-Python: >=3.6
Dynamic: author
Dynamic: author-email
Dynamic: classifier
Dynamic: description
Dynamic: description-content-type
Dynamic: home-page
Dynamic: license
Dynamic: requires-python
Dynamic: summary
